MANIFEST.in
README.txt
setup.cfg
setup.py
darcs_cgi.egg-info/PKG-INFO
darcs_cgi.egg-info/SOURCES.txt
darcs_cgi.egg-info/dependency_links.txt
darcs_cgi.egg-info/entry_points.txt
darcs_cgi.egg-info/not-zip-safe
darcs_cgi.egg-info/paster_plugins.txt
darcs_cgi.egg-info/requires.txt
darcs_cgi.egg-info/top_level.txt
darcscgi/__init__.py
darcscgi/websetup.py
darcscgi/config/__init__.py
darcscgi/config/deployment.ini_tmpl
darcscgi/config/environment.py
darcscgi/config/middleware.py
darcscgi/config/routing.py
darcscgi/controllers/__init__.py
darcscgi/controllers/error.py
darcscgi/controllers/information.py
darcscgi/controllers/repositories.py
darcscgi/controllers/template.py
darcscgi/lib/__init__.py
darcscgi/lib/app_globals.py
darcscgi/lib/base.py
darcscgi/lib/helpers.py
darcscgi/model/__init__.py
darcscgi/public/images/darcs-links-large.png
darcscgi/public/images/darcs-links-small.png
darcscgi/public/images/darcs-links.png
darcscgi/public/images/darcs-links.svg
darcscgi/public/images/darcs-server.png
darcscgi/public/images/favicon.ico
darcscgi/public/javascripts/event-handlers.js
darcscgi/public/javascripts/sort-table.js
darcscgi/public/static/default-configuration.xml
darcscgi/public/static/example-configuration.xml
darcscgi/templates/information/base.mako
darcscgi/templates/information/front.mako
darcscgi/templates/information/quarantine.mako
darcscgi/templates/information/repositories.mako
darcscgi/templates/stylesheets/compliant.mako
darcscgi/tests/__init__.py
darcscgi/tests/test_models.py
darcscgi/tests/functional/__init__.py
darcscgi/tests/functional/test_information.py
darcscgi/tests/functional/test_repositories.py
darcscgi/tests/functional/test_template.py