Metadata-Version: 1.0
Name: darcs-cgi
Version: 0.01.001dev
Summary: provides authenticated access to darcs repositories
Home-page: UNKNOWN
Author: orbisvicis
Author-email: orbisvicis@gmail.com
License: UNKNOWN
Platform: UNKNOWN
